setup.cfg
setup.py
bamboo/__init__.py
bamboo/addons.py
bamboo/converters.py
bamboo/core.py
bamboo/frames.py
bamboo/groups.py
bamboo/helpers.py
bamboo/plotting.py
bamboo/reports.py
bamboo/series_groups.py
bamboo/subplots.py
pandas_bamboo.egg-info/PKG-INFO
pandas_bamboo.egg-info/SOURCES.txt
pandas_bamboo.egg-info/dependency_links.txt
pandas_bamboo.egg-info/pbr.json
pandas_bamboo.egg-info/requires.txt
pandas_bamboo.egg-info/top_level.txt