Metadata-Version: 1.1
Name: pandas-bamboo
Version: 0.1.5
Summary: Data manipulation for python using Pandas
Home-page: https://github.com/ghl3/bamboo
Author: George Herbert Lewis
Author-email: ghl227@gmail.com
License: The MIT License: http://www.opensource.org/licenses/mit-license.php
Download-URL: https://github.com/ghl3/bamboo/tarball/0.1.2
Platform: UNKNOWN
